LICENSE
README.md
setup.py
cnfrm/__init__.py
cnfrm/config.py
cnfrm/exceptions.py
cnfrm/fields.py
cnfrm.egg-info/PKG-INFO
cnfrm.egg-info/SOURCES.txt
cnfrm.egg-info/dependency_links.txt
cnfrm.egg-info/top_level.txt