Metadata-Version: 2.1
Name: cnfrm
Version: 0.2.4
Summary: CnfRM - ORM for config
Home-page: https://github.com/hiaselhans/CnfRM
Author: hiaselhans
Author-email: simon.klemenc@gmail.com
License: UNKNOWN
Platform: UNKNOWN
Classifier: Programming Language :: Python :: 3
Classifier: License :: OSI Approved :: MIT License
Classifier: Operating System :: OS Independent
Requires-Python: >=3.6
